{
    "partidas": {
        "partida": [
            {
                "prenda": {
                    "cotitular": null,
                    "descripcion": "COLLAR TORZAL ORO BAJO GRAMOS 11.5 MEDALLA RELL D.I. ORO BAJO GRAMOS 14.7 GRAMOS TOTALES 26.2",
                    "folio": "105496203",
                    "montoAvaluo": 3415,
                    "montoPrestamo": 3350,
                    "ramo": "1 - Alhajas",
                    "subramo": "1 - Alhajas",
                    "sucursal": 0,
                    "tipoContrato": "145",
                    "titular": "TAMARA KARINARINCON BIBIANO",
                    "valuador": "Ernesto Valentin              Sanchez Cisneros"
                },
                "condiciones": {
                    "aplicaReempeno": true,
                    "contrato": 31,
                    "custodia": 0,
                    "estadoCaja": "Almoneda",
                    "estadoPrenda": "Refrendo Pagado",
                    "fechaComercializacion": "2017-06-20T21:52:31.312-05:00",
                    "fechaIngreso": "2017-06-20T21:52:31.312-05:00",
                    "fechaIngresoDeposito": "2017-06-20T21:52:31.312-05:00",
                    "fechaLimitePago": "2017-06-20T21:52:31.312-05:00",
                    "interes": 0,
                    "numeroMaximoRefrendos": 3,
                    "numeroRefrendosRealizados": 3,
                    "parametros": {
                        "Parametro": {
                            "parametro": "CAT",
                            "valor": "0.20"
                        }
                    },
                    "plazo": 0,
                    "reposicionBillete": {
                        "@nil": "true"
                    },
                    "tipoSeguro": 0
                },
                "saldoPL": {
                    "abonosCapital": 3350,
                    "comisionPendiente": 0,
                    "fecha": {
                        "@nil": "true"
                    },
                    "interesPendiente": 0,
                    "interesesPagados": 0,
                    "ivaSobreInteresPendiente": 0,
                    "saldoInsoluto": 0,
                    "ultimoAbono": {
                        "abonoCancelado": {
                            "@nil": "true"
                        },
                        "amortizacionUltimoAbono": 0,
                        "saldoInsolutoAnterior": 0
                    }
                },
                "comercial": {
                    "canalIngreso": "Cumplido",
                    "canalIngresoId": "6",
                    "fechaIngresoAlmoneda": "2017-06-20T21:52:31.297-05:00",
                    "precioVenta": 6978.56,
                    "utilidad": 0
                },
                "operaciones": {
                    "operacion": [
                        {
                            "tipoOperacion": "Refrendo",
                            "monto": 100.5
                        },
                        {
                            "tipoOperacion": "Desempeño",
                            "monto": 100.5
                        }
                    ]
                }
            },
            {
                "prenda": {
                    "cotitular": null,
                    "descripcion": "COLLAR 3X1 ORO MEDIANO GRAMOS 8.1",
                    "folio": "105498327",
                    "montoAvaluo": 3368,
                    "montoPrestamo": 3300,
                    "ramo": "1 - Alhajas",
                    "subramo": "1 - Alhajas",
                    "sucursal": 0,
                    "tipoContrato": "145",
                    "titular": "TAMARA KARINARINCON BIBIANO",
                    "valuador": "Ernesto Valentin              Sanchez Cisneros"
                },
                "condiciones": {
                    "aplicaReempeno": true,
                    "contrato": 31,
                    "custodia": 0,
                    "estadoCaja": "Almoneda",
                    "estadoPrenda": "Refrendo Pagado",
                    "fechaComercializacion": "2017-06-20T21:52:31.312-05:00",
                    "fechaIngreso": "2017-06-20T21:52:31.312-05:00",
                    "fechaIngresoDeposito": "2017-06-20T21:52:31.312-05:00",
                    "fechaLimitePago": "2017-06-20T21:52:31.312-05:00",
                    "interes": 0,
                    "numeroMaximoRefrendos": 3,
                    "numeroRefrendosRealizados": 3,
                    "parametros": {
                        "Parametro": {
                            "parametro": "CAT",
                            "valor": "0.20"
                        }
                    },
                    "plazo": 0,
                    "reposicionBillete": {
                        "@nil": "true"
                    },
                    "tipoSeguro": 0
                },
                "saldoPL": {
                    "abonosCapital": 3300,
                    "comisionPendiente": 0,
                    "fecha": {
                        "@nil": "true"
                    },
                    "interesPendiente": 0,
                    "interesesPagados": 0,
                    "ivaSobreInteresPendiente": 0,
                    "saldoInsoluto": 0,
                    "ultimoAbono": {
                        "abonoCancelado": {
                            "@nil": "true"
                        },
                        "amortizacionUltimoAbono": 0,
                        "saldoInsolutoAnterior": 0
                    }
                },
													"comercial": {
														"canalIngreso": "Cumplido",
														"canalIngresoId": "6",
														"fechaIngresoAlmoneda": "2017-06-20T21:52:31.312-05:00",
														"precioVenta": 6880,
														"utilidad": 0
													},
                "operaciones": {
                    "operacion": [
                        {
                            "tipoOperacion": "Refrendo",
                            "monto": 100.5
                        },
                        {
                            "tipoOperacion": "Desempeño",
                            "monto": 100.5
                        }
                    ]
                }
            },
            {
                "prenda": {
                    "cotitular": null,
                    "descripcion": "PULSERA ESLABON 1X1 ORO MED GRS 11.5...",
                    "folio": "105513627",
                    "montoAvaluo": 4207,
                    "montoPrestamo": 4000,
                    "ramo": "1 - Alhajas",
                    "subramo": "1 - Alhajas",
                    "sucursal": 0,
                    "tipoContrato": "145",
                    "titular": "MARIA GUADALUPEDIAZ CASTRO",
                    "valuador": "Ernesto Valentin              Sanchez Cisneros"
                },
                "condiciones": {
                    "aplicaReempeno": true,
                    "contrato": 31,
                    "custodia": 0,
                    "estadoCaja": "Almoneda",
                    "estadoPrenda": "Refrendo Pagado",
                    "fechaComercializacion": "2017-06-20T21:52:31.328-05:00",
                    "fechaIngreso": "2017-06-20T21:52:31.328-05:00",
                    "fechaIngresoDeposito": "2017-06-20T21:52:31.328-05:00",
                    "fechaLimitePago": "2017-06-20T21:52:31.328-05:00",
                    "interes": 0,
                    "numeroMaximoRefrendos": 3,
                    "numeroRefrendosRealizados": 3,
                    "parametros": {
                        "Parametro": {
                            "parametro": "CAT",
                            "valor": "0.20"
                        }
                    },
                    "plazo": 0,
                    "reposicionBillete": {
                        "@nil": "true"
                    },
                    "tipoSeguro": 0
                },
                "saldoPL": {
                    "abonosCapital": 4000,
                    "comisionPendiente": 0,
                    "fecha": {
                        "@nil": "true"
                    },
                    "interesPendiente": 0,
                    "interesesPagados": 0,
                    "ivaSobreInteresPendiente": 0,
                    "saldoInsoluto": 0,
                    "ultimoAbono": {
                        "abonoCancelado": {
                            "@nil": "true"
                        },
                        "amortizacionUltimoAbono": 0,
                        "saldoInsolutoAnterior": 0
                    }
                },
                "comercial": {
                    "canalIngreso": "Cumplido",
                    "canalIngresoId": "6",
                    "fechaIngresoAlmoneda": "2017-06-20T21:52:31.328-05:00",
                    "precioVenta": 8596.48,
                    "utilidad": 0
                },
                "operaciones": {
                    "operacion": [
                        {
                            "tipoOperacion": "Refrendo",
                            "monto": 100.5
                        },
                        {
                            "tipoOperacion": "Desempeño",
                            "monto": 100.5
                        }
                    ]
                }
            },
            {
                "prenda": {
                    "cotitular": null,
                    "descripcion": "DOS ARGS ORO BCO MEDIANO GRAMOS 6.2",
                    "folio": "105519079",
                    "montoAvaluo": 2269,
                    "montoPrestamo": 1700,
                    "ramo": "1 - Alhajas",
                    "subramo": "1 - Alhajas",
                    "sucursal": 0,
                    "tipoContrato": "145",
                    "titular": "JUAN ANTONIORIOS JASSO",
                    "valuador": "Vicencio                      Romero Gonzalez"
                },
                "condiciones": {
                    "aplicaReempeno": true,
                    "contrato": 31,
                    "custodia": 0,
                    "estadoCaja": "Almoneda",
                    "estadoPrenda": "Refrendo Pagado",
                    "fechaComercializacion": "2017-06-20T21:52:31.343-05:00",
                    "fechaIngreso": "2017-06-20T21:52:31.343-05:00",
                    "fechaIngresoDeposito": "2017-06-20T21:52:31.343-05:00",
                    "fechaLimitePago": "2017-06-20T21:52:31.343-05:00",
                    "interes": 0,
                    "numeroMaximoRefrendos": 3,
                    "numeroRefrendosRealizados": 3,
                    "parametros": {
                        "Parametro": {
                            "parametro": "CAT",
                            "valor": "0.20"
                        }
                    },
                    "plazo": 0,
                    "reposicionBillete": {
                        "@nil": "true"
                    },
                    "tipoSeguro": 0
                },
                "saldoPL": {
                    "abonosCapital": 1700,
                    "comisionPendiente": 0,
                    "fecha": {
                        "@nil": "true"
                    },
                    "interesPendiente": 0,
                    "interesesPagados": 0,
                    "ivaSobreInteresPendiente": 0,
                    "saldoInsoluto": 0,
                    "ultimoAbono": {
                        "abonoCancelado": {
                            "@nil": "true"
                        },
                        "amortizacionUltimoAbono": 0,
                        "saldoInsolutoAnterior": 0
                    }
                },
                "comercial": {
                    "canalIngreso": "Cumplido",
                    "canalIngresoId": "6",
                    "fechaIngresoAlmoneda": "2017-06-20T21:52:31.328-05:00",
                    "precioVenta": 4636.16,
                    "utilidad": 0
                },
                "operaciones": {
                    "operacion": [
                        {
                            "tipoOperacion": "Refrendo",
                            "monto": 100.5
                        },
                        {
                            "tipoOperacion": "Desempeño",
                            "monto": 100.5
                        }
                    ]
                }
            },
            {
                "prenda": {
                    "cotitular": null,
                    "descripcion": "COLLAR CON COLGANTE LETRAS PENDIENTE FORMA NIÃ‘A CON MOV ORO MEDIANO GRAMOS 4.2",
                    "folio": "105496743",
                    "montoAvaluo": 1537,
                    "montoPrestamo": 1500,
                    "ramo": "1 - Alhajas",
                    "subramo": "1 - Alhajas",
                    "sucursal": 0,
                    "tipoContrato": "145",
                    "titular": "YOLANDA OLIMPIACEDILLO PEREZ",
                    "valuador": "Ernesto Valentin              Sanchez Cisneros"
                },
                "condiciones": {
                    "aplicaReempeno": true,
                    "contrato": 31,
                    "custodia": 0,
                    "estadoCaja": "Almoneda",
                    "estadoPrenda": "Refrendo Pagado",
                    "fechaComercializacion": "2017-06-20T21:52:31.343-05:00",
                    "fechaIngreso": "2017-06-20T21:52:31.343-05:00",
                    "fechaIngresoDeposito": "2017-06-20T21:52:31.343-05:00",
                    "fechaLimitePago": "2017-06-20T21:52:31.343-05:00",
                    "interes": 0,
                    "numeroMaximoRefrendos": 3,
                    "numeroRefrendosRealizados": 3,
                    "parametros": {
                        "Parametro": {
                            "parametro": "CAT",
                            "valor": "0.20"
                        }
                    },
                    "plazo": 0,
                    "reposicionBillete": {
                        "@nil": "true"
                    },
                    "tipoSeguro": 0
                },
                "saldoPL": {
                    "abonosCapital": 1500,
                    "comisionPendiente": 0,
                    "fecha": {
                        "@nil": "true"
                    },
                    "interesPendiente": 0,
                    "interesesPagados": 0,
                    "ivaSobreInteresPendiente": 0,
                    "saldoInsoluto": 0,
                    "ultimoAbono": {
                        "abonoCancelado": {
                            "@nil": "true"
                        },
                        "amortizacionUltimoAbono": 0,
                        "saldoInsolutoAnterior": 0
                    }
                },
                "comercial": {
                    "canalIngreso": "Cumplido",
                    "canalIngresoId": "6",
                    "fechaIngresoAlmoneda": "2017-06-20T21:52:31.343-05:00",
                    "precioVenta": 3139.84,
                    "utilidad": 0
                },
                "operaciones": {
                    "operacion": [
                        {
                            "tipoOperacion": "Refrendo",
                            "monto": 100.5
                        },
                        {
                            "tipoOperacion": "Desempeño",
                            "monto": 100.5
                        }
                    ]
                }
            }
        ]
    }
}